Workbook

Sheet Suivi Journalier
A1: 🍽 SUIVI FINANCIER JOURNALIER — RESTAURANT
A2: Tableau de bord — April 2026
A4: DATE | B4: RECETTES | F4: DÉPENSES | J4: RETRAITS CARTE | M4: SOLDE THÉORIQUE | N4: OBSERVATIONS
A5: Date | B5: Recette Carte (Z Caisse) | C5: Recette Espèces (Z Caisse) | D5: Virement & Ticket Restau | E5: Total Recettes (AUTO) | F5: Dépenses Caisse (Espèces) | G5: Dépenses Carte (Pro) | H5: Dépenses TPE | I5: Total Dépenses (AUTO) | J5: Retraits Carte (Pro) | K5: Retraits Carte (Perso) | L5: Retraits Carte (Total) (AUTO) | M5: Solde Théorique (AUTO) | N5: Observations
A6: 02.04.2026 | B6: 4580 | C6: 4060 | E6: =SUM(B6:D6) -> 8640 | F6: 2040.88 | I6: =SUM(F6:H6) -> 2040.88 | K6: 2000 | L6: =SUM(J6:K6) -> 2000 | M6: =E6-(I6+L6) -> 4599.12
A7: 03.04.2026 | B7: 6655 | C7: 3710 | D7: 3455 | E7: =SUM(B7:D7) -> 13820 | F7: 2945 | I7: =SUM(F7:H7) -> 2945 | K7: 2000 | L7: =SUM(J7:K7) -> 2000 | M7: =E7-(I7+L7) -> 8875
A8: 04.04.2026 | B8: 3310 | C8: 2565 | E8: =SUM(B8:D8) -> 5875 | F8: 4195.63 | I8: =SUM(F8:H8) -> 4195.63 | J8: 2600 | K8: 400 | L8: =SUM(J8:K8) -> 3000 | M8: =E8-(I8+L8) -> -1320.63
A9: 05.04.2026 | B9: 4305 | C9: 1300 | E9: =SUM(B9:D9) -> 5605 | F9: 1175.5 | I9: 1175.5 | L9: =SUM(J9:K9) -> 0 | M9: =E9-(I9+L9) -> 4429.5
E10: =SUM(B10:D10) -> 0 | I10: =SUM(F10:H10) -> 0 | L10: =SUM(J10:K10) -> 0 | M10: =E10-(I10+L10) -> 0
E11: =SUM(B11:D11) -> 0 | I11: =SUM(F11:H11) -> 0 | L11: =SUM(J11:K11) -> 0 | M11: =E11-(I11+L11) -> 0
E12: =SUM(B12:D12) -> 0 | I12: =SUM(F12:H12) -> 0 | L12: =SUM(J12:K12) -> 0 | M12: =E12-(I12+L12) -> 0
E13: =SUM(B13:D13) -> 0 | I13: =SUM(F13:H13) -> 0 | L13: =SUM(J13:K13) -> 0 | M13: =E13-(I13+L13) -> 0
E14: =SUM(B14:D14) -> 0 | I14: =SUM(F14:H14) -> 0 | L14: =SUM(J14:K14) -> 0 | M14: =E14-(I14+L14) -> 0
E15: =SUM(B15:D15) -> 0 | I15: =SUM(F15:H15) -> 0 | L15: =SUM(J15:K15) -> 0 | M15: =E15-(I15+L15) -> 0
E16: =SUM(B16:D16) -> 0 | I16: =SUM(F16:H16) -> 0 | L16: =SUM(J16:K16) -> 0 | M16: =E16-(I16+L16) -> 0
E17: =SUM(B17:D17) -> 0 | I17: =SUM(F17:H17) -> 0 | L17: =SUM(J17:K17) -> 0 | M17: =E17-(I17+L17) -> 0
E18: =SUM(B18:D18) -> 0 | I18: =SUM(F18:H18) -> 0 | L18: =SUM(J18:K18) -> 0 | M18: =E18-(I18+L18) -> 0
E19: =SUM(B19:D19) -> 0 | I19: =SUM(F19:H19) -> 0 | L19: =SUM(J19:K19) -> 0 | M19: =E19-(I19+L19) -> 0
E20: =SUM(B20:D20) -> 0 | I20: =SUM(F20:H20) -> 0 | L20: =SUM(J20:K20) -> 0 | M20: =E20-(I20+L20) -> 0
E21: =SUM(B21:D21) -> 0 | I21: =SUM(F21:H21) -> 0 | L21: =SUM(J21:K21) -> 0 | M21: =E21-(I21+L21) -> 0
... E36: =SUM(B36:D36) -> 0 | I36: =SUM(F36:H36) -> 0 | L36: =SUM(J36:K36) -> 0 | M36: =E36-(I36+L36) -> 0
A37: TOTAUX MENSUELS | B37: =SUM(B6:B36) -> 18850 | C37: =SUM(C6:C36) -> 11635 | D37: =SUM(D6:D36) -> 3455 | E37: =SUM(E6:E36) -> 33940 | F37: =SUM(E6:E36) -> 33940 | G37: =SUM(F6:F36) -> 10357.01 | H37: =SUM(G6:G36) -> 0 | I37: =SUM(I6:I36) -> 10357.01 | J37: =SUM(H6:H36) -> 0 | K37: =SUM(I6:I36) -> 10357.01 | L37: =SUM(L6:L36) -> 7000 | M37: =SUM(M6:M36) -> 16582.99

Sheet Légende & Instructions
A1: LÉGENDE DES COULEURS ET INSTRUCTIONS
A3: COULEURS DES CELLULES
A4: Texte bleu | B4: Saisie manuelle (données à entrer par l'utilisateur)
A5: Texte noir gras | B5: Calcul automatique (ne pas modifier)
A7: COLONNES — DÉFINITIONS
A8: Date | B8: Date du jour (format JJ/MM/AAAA)
A9: Recette Carte | B9: Montant des recettes carte bancaire selon le Z de caisse
A10: Recette Espèces | B10: Montant des recettes espèces selon le Z de caisse
A11: Virement & Ticket Restau | B11: Montant des virements et tickets restaurant reçus
A12: Total Recettes | B12: Recette Carte + Recette Espèces (calcul automatique)
A13: Dépenses Caisse | B13: Dépenses réglées en espèces, issues de la feuille du manager
A14: Dépenses Carte (Pro) | B14: Dépenses professionnelles du restaurant réglées par carte
A15: Dépenses TPE | B15: Dépenses réglées via le terminal de paiement électronique (TPE)
A16: Total Dépenses | B16: Dépenses Caisse + Dépenses Carte Pro + Dépenses TPE (calcul automatique)
A17: Retraits Carte (Total) | B17: Retraits Pro + Retraits Perso (calcul automatique)
A18: Retraits Carte (Pro) | B18: Part professionnelle des retraits carte (entrer la valeur)
A19: Retraits Carte (Perso) | B19: Part personnelle des retraits carte (entrer la valeur)
A20: Solde Théorique
A21: Observations
A23: BONNES PRATIQUES
A24: ✔ | B24: Saisir les données chaque soir après fermeture de caisse
A25: ✔ | B25: Vérifier que Retraits Total = Retraits Pro + Retraits Perso
A26: ✔ | B26: Conserver les tickets et reçus correspondants aux dépenses carte
A27: ✔ | B27: Contrôler le Solde Théorique avec le solde réel du compte en banque
A28: ✔ | B28: Utiliser la colonne Observations pour signaler tout écart

Sheet Récap Mensuel
A1: RÉCAPITULATIF MENSUEL
A2: Indicateur | B2: Montant (MAD) | C2: % du Total Recettes
A3: Total Recettes Carte | B3: ='Suivi Journalier'!B37 -> 18850
A4: Total Recettes Espèces | B4: ='Suivi Journalier'!C37 -> 11635
A5: Total Virement & Ticket Restau | B5: ='Suivi Journalier'!D37 -> 3455 | C5: =IFERROR(B5/B6,"-") -> 0.10179729
A6: TOTAL RECETTES | B6: ='Suivi Journalier'!E37 -> 33940 | C6: 1
A7: Total Dépenses Caisse | B7: ='Suivi Journalier'!E37 -> 33940 | C7: =IFERROR(B7/B6,"-") -> 1
A8: Total Dépenses Carte Pro | B8: ='Suivi Journalier'!F37 -> 33940 | C8: =IFERROR(B8/B6,"-") -> 1
A9: Total Dépenses TPE | B9: ='Suivi Journalier'!G37 -> 10357.01 | C9: =IFERROR(B9/B6,"-") -> 0.30515645
A10: TOTAL DÉPENSES | B10: ='Suivi Journalier'!H37 -> 0 | C10: =IFERROR(B10/B6,"-") -> 0
A11: Total Retraits Pro | B11: ='Suivi Journalier'!I37 -> 10357.01 | C11: =IFERROR(B11/B6,"-") -> 0.30515645
A12: Total Retraits Perso | B12: ='Suivi Journalier'!J37 -> 0 | C12: =IFERROR(B12/B6,"-") -> 0
A13: TOTAL RETRAITS | B13: ='Suivi Journalier'!K37 -> 10357.01 | C13: =IFERROR(B13/B6,"-") -> 0.30515645
A14: SOLDE THÉORIQUE MENSUEL | B14: ='Suivi Journalier'!L37 -> 7000 | C14: =IFERROR(B14/B6,"-") -> 0.20624632
